{
  "code": "nn",
  "name": "Norwegian Nynorsk",
  "family": "Germanic",
  "script": "Latin",
  "graphemes_base": "no",
  "allophones_base": "no",
  "allophones": {
    "r": [
      "r"
    ],
    "rn": [
      "rn",
      "ɳ"
    ],
    "ej": [
      "ej"
    ],
    "au": [
      "au"
    ],
    "øy": [
      "øy"
    ]
  },
  "parent": "no",
  "notes": "Norwegian Nynorsk — minority written standard (~15%). Based on western Norwegian dialects. Alveolar /r/ [r]; less retroflexion than Bokmål/Eastern. More diphthongs preserved from Old Norse: ei, au, øy. Source: Kristoffersen (2000).",
  "quality": "skeleton",
  "script_type": "alphabet",
  "sources": [
    {
      "id": "haugen1976",
      "author": "Haugen, E.",
      "year": 1976,
      "title": "The Scandinavian Languages: An Introduction to their History",
      "publisher": "Faber and Faber",
      "url": null,
      "pages": null,
      "notes": null
    },
    {
      "id": "kristoffersen2000",
      "author": "Kristoffersen, G.",
      "year": 2000,
      "title": "The Phonology of Norwegian",
      "publisher": "Oxford University Press",
      "url": null,
      "pages": null,
      "notes": null
    }
  ]
}
